lauscher/__init__.py
lauscher/__main__.py
lauscher/abstract.py
lauscher/audiowaves.py
lauscher/firing_probability.py
lauscher/helpers.py
lauscher/membranevelocity.py
lauscher/spike_train.py
lauscher/transformations/__init__.py
lauscher/transformations/basilar_membrane.py
lauscher/transformations/bushy_cell.py
lauscher/transformations/hair_cell.py
lauscher/transformations/peak_normalizer.py
lauscher/transformations/rms_normalizer.py
lauscher/transformations/wave2spike.py
lauscher/transformations/window.py
lauscher-1.0.1.dist-info/licenses/LICENSE
lauscher-1.0.1.dist-info/METADATA
lauscher-1.0.1.dist-info/WHEEL
lauscher-1.0.1.dist-info/entry_points.txt
lauscher-1.0.1.dist-info/top_level.txt
lauscher-1.0.1.dist-info/RECORD
