Metadata-Version: 2.4
Name: lauscher
Version: 1.0.1
Summary: Transform audio waveforms into spike trains using a biologically-plausible cochlea model.
Author-email: Benjamin Cramer <benjamin.cramer@kip.uni-heidelberg.de>, Yannik Stradmann <yannik.stradmann@kip.uni-heidelberg.de>, Friedemann Zenke <friedemann.zenke@fmi.ch>, Koshika Yadava <koshika@stanford.edu>
License-Expression: LGPL-2.1-only
Project-URL: Homepage, https://github.com/electronicvisions/lauscher
Project-URL: Repository, https://github.com/electronicvisions/lauscher
Requires-Python: >=3.7
License-File: LICENSE
Requires-Dist: soundfile
Requires-Dist: numpy
Requires-Dist: matplotlib
Requires-Dist: scipy
Requires-Dist: numba
Dynamic: license-file
